tkfilterlist/__init__.py
tkfilterlist/__main__.py
tkfilterlist/widget.py
tkFilterList-0.1.2.dist-info/LICENSE
tkFilterList-0.1.2.dist-info/METADATA
tkFilterList-0.1.2.dist-info/WHEEL
tkFilterList-0.1.2.dist-info/top_level.txt
tkFilterList-0.1.2.dist-info/RECORD
