Metadata-Version: 2.1
Name: tkFilterList
Version: 0.1.2
Summary: Self-filtering Listbox with text entry for Tkinter
Home-page: https://github.com/bmjcode/tkFilterList
Author: Benjamin Johnson
Author-email: bmjcode@gmail.com
License: UNKNOWN
Platform: UNKNOWN
Classifier: Development Status :: 4 - Beta
Classifier: Programming Language :: Python :: 2
Classifier: Programming Language :: Python :: 3
Classifier: License :: OSI Approved :: MIT License
Classifier: Operating System :: OS Independent
